PieODS/Adapter.py
PieODS/Notification.py
PieODS/PieODS.py
PieODS/Pipeline.py
PieODS/Storage.py
PieODS/Switch.py
PieODS/__init__.py
PieODS/cli.py
PieODS/data_structs.py
PieODS/helpers.py
PieODS-1.0.1.dist-info/AUTHORS.rst
PieODS-1.0.1.dist-info/LICENSE
PieODS-1.0.1.dist-info/METADATA
PieODS-1.0.1.dist-info/WHEEL
PieODS-1.0.1.dist-info/entry_points.txt
PieODS-1.0.1.dist-info/top_level.txt
PieODS-1.0.1.dist-info/RECORD
