Metadata-Version: 2.1
Name: PieODS
Version: 1.0.1
Summary: Python interface to the Open Data Service API
Home-page: https://github.com/Shady-Hegazy/PieODS
Author: Shady Hegazy
Author-email: shadi.hegazy@gmail.com
License: MIT license
Keywords: PieODS
Platform: UNKNOWN
Classifier: Development Status :: 2 - Pre-Alpha
Classifier: Intended Audience :: Developers
Classifier: License :: OSI Approved :: MIT License
Classifier: Natural Language :: English
Classifier: Programming Language :: Python :: 3
Classifier: Programming Language :: Python :: 3.5
Classifier: Programming Language :: Python :: 3.6
Classifier: Programming Language :: Python :: 3.7
Classifier: Programming Language :: Python :: 3.8
Requires-Python: >=3.5
Requires-Dist: Click (>=7.0)
Requires-Dist: requests (>=2.7.0)
